robobo_emotion/__init__.py
robobo_emotion/emotion_audio.py
robobo_emotion/emotion_image.py
robobo_emotion/robobo_multimodal_emotion.py
robobo_multimodal_emotion/__init__.py
robobo_multimodal_emotion/robobo_multimodal_emotion.py
robobo_emotion-0.7.dist-info/METADATA
robobo_emotion-0.7.dist-info/WHEEL
robobo_emotion-0.7.dist-info/top_level.txt
robobo_emotion-0.7.dist-info/RECORD
