Metadata-Version: 2.1
Name: robobo-emotion
Version: 0.7
Summary: Librería para detectar emociones en imágenes y audio usando Robobo
Home-page: https://github.com/Calza36/roboboemotions
Author: Ernesto Calzadilla
Classifier: Programming Language :: Python :: 3
Classifier: License :: OSI Approved :: MIT License
Classifier: Operating System :: OS Independent
Requires-Python: >=3.8
Requires-Dist: absl-py ==2.1.0
Requires-Dist: addict ==2.4.0
Requires-Dist: aiohttp ==3.9.5
Requires-Dist: aiosignal ==1.3.1
Requires-Dist: aliyun-python-sdk-core ==2.15.1
Requires-Dist: aliyun-python-sdk-kms ==2.16.3
Requires-Dist: antlr4-python3-runtime ==4.9.3
Requires-Dist: astunparse ==1.6.3
Requires-Dist: async-timeout ==4.0.3
Requires-Dist: attrs ==23.2.0
Requires-Dist: audioread ==3.0.1
Requires-Dist: beartype ==0.18.5
Requires-Dist: beautifulsoup4 ==4.12.3
Requires-Dist: blinker ==1.8.2
Requires-Dist: certifi ==2024.6.2
Requires-Dist: cffi ==1.16.0
Requires-Dist: charset-normalizer ==3.3.2
Requires-Dist: click ==8.1.7
Requires-Dist: colorama ==0.4.6
Requires-Dist: crcmod ==1.7
Requires-Dist: cryptography ==42.0.8
Requires-Dist: datasets ==2.18.0
Requires-Dist: decorator ==5.1.1
Requires-Dist: deepface ==0.0.92
Requires-Dist: dill ==0.3.8
Requires-Dist: editdistance ==0.8.1
Requires-Dist: einops ==0.8.0
Requires-Dist: filelock ==3.15.3
Requires-Dist: fire ==0.6.0
Requires-Dist: Flask ==3.0.3
Requires-Dist: flatbuffers ==24.3.25
Requires-Dist: frozenlist ==1.4.1
Requires-Dist: fsspec ==2024.2.0
Requires-Dist: funasr ==1.0.28
Requires-Dist: gast ==0.5.4
Requires-Dist: gdown ==5.2.0
Requires-Dist: google-pasta ==0.2.0
Requires-Dist: grpcio ==1.64.1
Requires-Dist: gunicorn ==22.0.0
Requires-Dist: h5py ==3.11.0
Requires-Dist: huggingface-hub ==0.23.4
Requires-Dist: hydra-core ==1.3.2
Requires-Dist: idna ==3.7
Requires-Dist: importlib-metadata ==7.2.0
Requires-Dist: intel-openmp ==2021.4.0
Requires-Dist: itsdangerous ==2.2.0
Requires-Dist: jaconv ==0.3.4
Requires-Dist: jamo ==0.4.1
Requires-Dist: jieba ==0.42.1
Requires-Dist: Jinja2 ==3.1.4
Requires-Dist: jmespath ==0.10.0
Requires-Dist: joblib ==1.4.2
Requires-Dist: kaldiio ==2.18.0
Requires-Dist: keras ==3.3.3
Requires-Dist: lazy-loader ==0.4
Requires-Dist: libclang ==18.1.1
Requires-Dist: librosa ==0.10.2.post1
Requires-Dist: llvmlite ==0.43.0
Requires-Dist: Markdown ==3.6
Requires-Dist: markdown-it-py ==3.0.0
Requires-Dist: MarkupSafe ==2.1.5
Requires-Dist: mdurl ==0.1.2
Requires-Dist: mkl ==2021.4.0
Requires-Dist: ml-dtypes ==0.3.2
Requires-Dist: modelscope ==1.15.0
Requires-Dist: more-itertools ==10.3.0
Requires-Dist: mpmath ==1.3.0
Requires-Dist: msgpack ==1.0.8
Requires-Dist: mtcnn ==0.1.1
Requires-Dist: multidict ==6.0.5
Requires-Dist: multiprocess ==0.70.16
Requires-Dist: namex ==0.0.8
Requires-Dist: networkx ==3.3
Requires-Dist: numba ==0.60.0
Requires-Dist: numpy ==1.26.4
Requires-Dist: omegaconf ==2.3.0
Requires-Dist: openai-whisper ==20231117
Requires-Dist: opencv-python ==4.10.0.84
Requires-Dist: opt-einsum ==3.3.0
Requires-Dist: optree ==0.11.0
Requires-Dist: oss2 ==2.18.6
Requires-Dist: packaging ==24.1
Requires-Dist: pandas ==2.2.2
Requires-Dist: pillow ==10.3.0
Requires-Dist: platformdirs ==4.2.2
Requires-Dist: pooch ==1.8.2
Requires-Dist: protobuf ==4.25.3
Requires-Dist: pyarrow ==16.1.0
Requires-Dist: pyarrow-hotfix ==0.6
Requires-Dist: pycparser ==2.22
Requires-Dist: pycryptodome ==3.20.0
Requires-Dist: Pygments ==2.18.0
Requires-Dist: pynndescent ==0.5.13
Requires-Dist: PySocks ==1.7.1
Requires-Dist: python-dateutil ==2.9.0.post0
Requires-Dist: pytorch-wpe ==0.0.1
Requires-Dist: pytz ==2024.1
Requires-Dist: PyYAML ==6.0.1
Requires-Dist: regex ==2024.5.15
Requires-Dist: requests ==2.32.3
Requires-Dist: retina-face ==0.0.17
Requires-Dist: rich ==13.7.1
Requires-Dist: rotary-embedding-torch ==0.6.2
Requires-Dist: scikit-learn ==1.5.0
Requires-Dist: scipy ==1.13.1
Requires-Dist: sentencepiece ==0.2.0
Requires-Dist: simplejson ==3.19.2
Requires-Dist: six ==1.16.0
Requires-Dist: sortedcontainers ==2.4.0
Requires-Dist: soundfile ==0.12.1
Requires-Dist: soupsieve ==2.5
Requires-Dist: soxr ==0.3.7
Requires-Dist: sympy ==1.12.1
Requires-Dist: tbb ==2021.13.0
Requires-Dist: tensorboard ==2.16.2
Requires-Dist: tensorboard-data-server ==0.7.2
Requires-Dist: tensorboardX ==2.6.2.2
Requires-Dist: tensorflow ==2.16.1
Requires-Dist: tensorflow-intel ==2.16.1
Requires-Dist: tensorflow-io-gcs-filesystem ==0.31.0
Requires-Dist: termcolor ==2.4.0
Requires-Dist: tf-keras ==2.16.0
Requires-Dist: threadpoolctl ==3.5.0
Requires-Dist: tiktoken ==0.7.0
Requires-Dist: tomli ==2.0.1
Requires-Dist: torch ==2.3.1
Requires-Dist: torch-complex ==0.4.3
Requires-Dist: torchaudio ==2.3.1
Requires-Dist: tqdm ==4.66.4
Requires-Dist: typing-extensions ==4.12.2
Requires-Dist: tzdata ==2024.1
Requires-Dist: umap-learn ==0.5.6
Requires-Dist: urllib3 ==2.2.2
Requires-Dist: Werkzeug ==3.0.3
Requires-Dist: wrapt ==1.16.0
Requires-Dist: xxhash ==3.4.1
Requires-Dist: yapf ==0.40.2
Requires-Dist: yarl ==1.9.4
Requires-Dist: zipp ==3.19.2
